setup.cfg
setup.py
earthpic/__init__.py
earthpic/constants.py
earthpic/earth.py
earthpic/himawari8.py
earthpic/utils.py
earthpic.egg-info/PKG-INFO
earthpic.egg-info/SOURCES.txt
earthpic.egg-info/dependency_links.txt
earthpic.egg-info/entry_points.txt
earthpic.egg-info/requires.txt
earthpic.egg-info/top_level.txt
earthpic/tests/__init__.py