Metadata-Version: 1.1
Name: earthpic
Version: 0.3
Summary: Earth photos downloader
Home-page: https://github.com/pywkm/earthpic
Author: Wiktor Matuszewski
Author-email: pywkm@wukaem.pl
License: BSD
Platform: Windows
Classifier: Topic :: Multimedia :: Graphics
Classifier: Development Status :: 4 - Beta
Classifier: Environment :: Console
Classifier: Environment :: Win32 (MS Windows)
Classifier: Operating System :: Microsoft :: Windows
Classifier: Operating System :: Microsoft :: Windows :: Windows 7
Classifier: License :: OSI Approved :: BSD License
Classifier: Programming Language :: Python
Classifier: Programming Language :: Python :: 3
Classifier: Programming Language :: Python :: 3.3
Classifier: Programming Language :: Python :: 3.5
Classifier: Programming Language :: Python :: 3 :: Only
